{
    "node_id":  "FIN-CASCADE-009-NETWORK-SUPPRESSION-AUDIT",
    "case_anchor":  "CASE-MACHERET-1997-2026",
    "un_ref":  "tw571ryb",
    "victim_idnp":  "2000001159655",
    "forensic_incident_log":  {
                                  "provider":  "StarNet Moldova",
                                  "evidence":  "HTTP 302 Redirection to avertizare.starnet.md",
                                  "event_type":  "Transparent Proxy Interception / DPI",
                                  "payload_tampering":  "Received 3818-byte fake packets in APT hashes (Status: suppression attempt)"
                              },
    "protocol_impact":  {
                            "blocked_ports":  "587 (STARTTLS), 443 (API-HTTPS filters)",
                            "confirmed_nodes_secured":  "Node 006 (d88794a), Node 007 (258f8b5), Node 008 (c52c28d)",
                            "bypass_status":  "SSH Port 22 (Git Push) - SUCCESSFUL"
                        },
    "corrective_measures":  {
                                "security_protocol":  "Forced TLS 1.3 / 1.2 in PowerShell environment",
                                "smtp_reconfiguration":  "Switching to Port 465 (Direct SSL) to bypass StarNet HTTP-proxy filters"
                            },
    "strategic_conclusion":  "Interference detected immediately after RRN 019811057850 forgery disclosure. Confirmation of panic in the \u0027Kiev 3a\u0027 hub.",
    "integrity":  "SHA-256 Sealed by A©tor Key 7BEACB5463BA3007"
}
